LICENSE
MANIFEST.in
README
setup.cfg
setup.py
deployer/__init__.py
deployer/charm.py
deployer/cli.py
deployer/config.py
deployer/deployment.py
deployer/errors.py
deployer/feedback.py
deployer/guiserver.py
deployer/relation.py
deployer/service.py
deployer/utils.py
deployer/vcs.py
deployer/action/__init__.py
deployer/action/base.py
deployer/action/diff.py
deployer/action/export.py
deployer/action/importer.py
deployer/env/__init__.py
deployer/env/base.py
deployer/env/go.py
deployer/env/gui.py
deployer/env/mem.py
deployer/env/py.py
deployer/env/watchers.py
deployer/tests/__init__.py
deployer/tests/base.py
deployer/tests/test_base.py
deployer/tests/test_charm.py
deployer/tests/test_config.py
deployer/tests/test_constraints.py
deployer/tests/test_deployment.py
deployer/tests/test_diff.py
deployer/tests/test_goenv.py
deployer/tests/test_guienv.py
deployer/tests/test_guiserver.py
deployer/tests/test_importer.py
deployer/tests/test_pyenv.py
deployer/tests/test_service.py
deployer/tests/test_utils.py
deployer/tests/test_watchers.py
deployer/tests/test_data/blog-haproxy-services.yaml
deployer/tests/test_data/blog.snippet
deployer/tests/test_data/blog.yaml
deployer/tests/test_data/negative.cfg
deployer/tests/test_data/negative.yaml
deployer/tests/test_data/stack-default.cfg
deployer/tests/test_data/stack-include.template
deployer/tests/test_data/stack-include.yaml
deployer/tests/test_data/stack-includes.cfg
deployer/tests/test_data/stack-inherits.cfg
deployer/tests/test_data/stack-placement-invalid-2.yaml
deployer/tests/test_data/stack-placement-invalid-subordinate.yaml
deployer/tests/test_data/stack-placement-invalid.yaml
deployer/tests/test_data/stack-placement-maas.yml
deployer/tests/test_data/stack-placement.yaml
deployer/tests/test_data/wiki-bindings.yaml
deployer/tests/test_data/wiki-resources.yaml
deployer/tests/test_data/wiki-storage.yaml
deployer/tests/test_data/wiki.yaml
deployer/tests/test_data/openstack/openstack-1501.yaml
juju_deployer.egg-info/PKG-INFO
juju_deployer.egg-info/SOURCES.txt
juju_deployer.egg-info/dependency_links.txt
juju_deployer.egg-info/entry_points.txt
juju_deployer.egg-info/requires.txt
juju_deployer.egg-info/top_level.txt