Metadata-Version: 1.1
Name: juju-deployer
Version: 0.11.0
Summary: A tool for deploying complex stacks with juju.
Home-page: http://launchpad.net/juju-deployer
Author: Kapil Thangavelu
Author-email: kapil.foss@gmail.com
License: UNKNOWN
Platform: UNKNOWN
Classifier: Development Status :: 4 - Beta
Classifier: Programming Language :: Python
Classifier: Programming Language :: Python :: 2
Classifier: Programming Language :: Python :: 2.7
Classifier: Programming Language :: Python :: 3
Classifier: Programming Language :: Python :: 3.5
Classifier: Topic :: Internet
Classifier: Topic :: Software Development :: Libraries :: Python Modules
Classifier: Intended Audience :: System Administrators
Classifier: Intended Audience :: Developers
